{
  "project_info": {
    "project_number": "105510107150",
    "project_id": "krasn-f1487",
    "storage_bucket": "krasn-f1487.appspot.com"
  },
  "client": [
    {
      "client_info": {
        "mobilesdk_app_id": "1:105510107150:android:c0d1f6ccd3389ebe95245f",
        "android_client_info": {
          "package_name": "clicdappsv.omigl"
        }
      },
      "oauth_client": [
        {
          "client_id": "105510107150-5sphla9223jo1spruf7dg2price1ca1p.apps.googleusercontent.com",
          "client_type": 3
        }
      ],
      "api_key": [
        {
          "current_key": "AIzaSyDooFhaqRpwLpYIeJ7EOnWhV3zsY0UCHe4"
        }
      ],
      "services": {
        "appinvite_service": {
          "other_platform_oauth_client": [
            {
              "client_id": "105510107150-5sphla9223jo1spruf7dg2price1ca1p.apps.googleusercontent.com",
              "client_type": 3
            }
          ]
        }
      }
    }
  ],
  "configuration_version": "1"
}